Package2/__init__.py
package1/__init__.py
package3/__init__.py
myPackage_646-0.0.0.dist-info/METADATA
myPackage_646-0.0.0.dist-info/WHEEL
myPackage_646-0.0.0.dist-info/top_level.txt
myPackage_646-0.0.0.dist-info/RECORD
