Metadata-Version: 2.1
Name: myPackage-646
Version: 0.0.0
Summary: This is my package
Author: Me
